bineurones/__init__.py
bineurones/multineurone.py
bineurones/neurone.py
bineurones-0.1.4.dist-info/METADATA
bineurones-0.1.4.dist-info/WHEEL
bineurones-0.1.4.dist-info/top_level.txt
bineurones-0.1.4.dist-info/RECORD
